[{"__symbolic":"module","version":4,"metadata":{},"exports":[{"from":"./index"},{"from":"./lib/components/account-layout/account-layout.component","export":[{"name":"AccountLayoutComponent","as":"ɵb"}]},{"from":"./lib/components/application-layout/application-layout.component","export":[{"name":"ApplicationLayoutComponent","as":"ɵa"}]},{"from":"./lib/providers/styles.provider","export":[{"name":"NGALAINMS_THEME_STYLES_PROVIDERS","as":"ɵl"},{"name":"configureStyles","as":"ɵm"}]},{"from":"./lib/root/global-config.module","export":[{"name":"GlobalConfigModule","as":"ɵd"}]},{"from":"./lib/root/providers/lang.provider","export":[{"name":"LANG","as":"ɵh"},{"name":"LANG_PROVIDES","as":"ɵi"}]},{"from":"./lib/root/providers/startup.service","export":[{"name":"APPINIT_PROVIDES","as":"ɵg"},{"name":"StartupService","as":"ɵe"},{"name":"StartupServiceFactory","as":"ɵf"}]},{"from":"./lib/root/providers/styles.provider","export":[{"name":"STYLES_PROVIDERS","as":"ɵj"},{"name":"configureStyles","as":"ɵk"}]},{"from":"./lib/root/root.module","export":[{"name":"RootModule","as":"ɵc"}]}]}]