{
  "culture": "zh-Hant",
  "texts": {
    "Volo.Abp.Identity:010001": "您無法刪除自己的帳戶!",
    "Permission:IdentityManagement": "身份標識管理",
    "Permission:RoleManagement": "角色管理",
    "Permission:ClaimManagement": "聲明管理",
    "Permission:Create": "建立",
    "Permission:Edit": "編輯",
    "Permission:Delete": "刪除",
    "Permission:ChangePermissions": "更改許可權",
    "Permission:ViewChangeHistory": "檢視變更記錄",
    "Permission:UserManagement": "使用者管理",
    "Permission:SettingManagement": "設定管理",
    "Permission:OrganizationUnitManagement": "組織機構管理",
    "Permission:ManageOU": "管理組織機構樹",
    "Permission:ManageUsers": "管理使用者",
    "Permission:ManageRoles": "角色",
    "Permission:SecurityLogs": "安全日誌",
    "Menu:SecurityLogs": "安全日誌",
    "Menu:IdentityManagement": "身份標識管理",
    "Users": "使用者",
    "Lock": "鎖定",
    "Unlock": "解鎖",
    "UserLockoutNotEnabled{0}": "使用者 '{0}' 鎖定功能沒有啟用!",
    "TwoFactor":"雙因素驗證",
    "DisplayName:TwoFactorEnabled": "啟用雙因素驗證",
    "NewUser": "新使用者",
    "Name": "名稱",
    "UserName": "使用者名稱",
    "EmailAddress": "郵箱地址",
    "PhoneNumber": "手機號碼",
    "UserInformation": "使用者資訊",
    "ClaimTypes": "聲明型別",
    "Roles": "角色",
    "Roles{0}": "角色 ({0})",
    "Members": "成員",
    "OrganizationUnits": "組織機構",
    "OrganizationUnits{0}": "組織機構({0})",
    "OrganizationUnit:Parent{0}": "父機構: {0}",
    "OrganizationUnit:Root": "根機構",
    "Type": "型別",
    "Claims": "聲明",
    "NewClaimType": "新聲明型別",
    "ValueType": "值型別",
    "Description": "描述",
    "Required": "必要",
    "Regex": "正則",
    "RegexDescription": "正則描述",
    "IsStatic": "是否靜態",
    "ClaimTypeDeletionConfirmationMessage": "聲明型別「{0}」將被刪除.你確認了嗎?",
    "Password": "密碼",
    "UserDeletionConfirmationMessage": "使用者「{0}」將被刪除. 你確認了嗎?",
    "RoleDeletionConfirmationMessage": "角色「{0}」將被刪除. 你確認了嗎?",
    "OrganizationUnitDeletionConfirmationMessage": "你確定要刪除組織機構'{0}'?",
    "SelectUsers": "選擇使用者",
    "SelectRoles": "選擇角色",
    "DisplayName:RoleName": "角色名稱",
    "DisplayName:IsDefault": "預設",
    "DisplayName:IsStatic": "靜態",
    "DisplayName:IsPublic": "公開",
    "DisplayName:UserName": "使用者名稱",
    "DisplayName:Email": "信箱",
    "DisplayName:Name": "名",
    "DisplayName:Surname": "姓",
    "DisplayName:Password": "密碼",
    "DisplayName:EmailAddress": "郵箱地址",
    "DisplayName:PhoneNumber": "手機號碼",
    "DisplayName:LockoutEnabled": "登錄嘗試失敗后鎖定帳戶",
    "SelectAnOrganizationUnitToSeeMembers": "選擇一個組織機構來檢視成員",
    "SelectAnOrganizationUnitToSeeRoles": "選擇一個組織機構來檢視角色",
    "RemoveUserFromOuWarningMessage": "你確定要從組織機構{1}中刪除使用者{0}嗎?",
    "RemoveRoleFromOuWarningMessage": "您確定要從組織機構{1}中刪除角色{0}嗎?",
    "OrganizationTree": "組織機構",
    "AddRootUnit": "新增根機構",
    "AddSubUnit": "新增子機構",
    "AddRole": "新增角色",
    "AddMember": "新增成員",
    "NewRole": "新角色",
    "RoleName": "角色名稱",
    "CreationTime": "建立時間",
    "Permissions": "權限",
    "DisplayName:CurrentPassword": "目前密碼",
    "DisplayName:NewPassword": "新密碼",
    "DisplayName:NewPasswordConfirm": "確認新密碼",
    "GenerateRandomPasswordTooltip": "產生亂數密碼",
    "PasswordChangedMessage": "密碼修改成功.",
    "SavedSuccessfully": "儲存成功",
    "PasswordSettings": "密碼設定",
    "SetPassword": "設定密碼",
    "PasswordsAreNotSame": "指定的密碼不相同.",
    "UserNotFound": "使用者不存在",
    "LockoutSettings": "鎖定設定",
    "SignInSettings": "登錄設定",
    "UserSettings": "使用者設定",
    "DisplayName:LockDurationType": "鎖定時間型別",
    "Enum:LockDurationType.Second": "秒",
    "Enum:LockDurationType.Minute": "分鐘",
    "Enum:LockDurationType.Hour": "小時",
    "Enum:LockDurationType.Day": "天",
    "Enum:LockDurationType.Month": "月",
    "Enum:LockDurationType.Year": "年",
    "ThisUserIsLockedOutMessage": "此使用者已被鎖定. 要解鎖,請單擊「操作」,然後單擊「解鎖」.",
    "UserUnlocked": "使用者解鎖.",
    "AddClaim": "新增聲明",
    "ChangeHistory": "變更歷史",
    "NewOrganizationUnit": "新組織機構",
    "DisplayName": "顯示名稱",
    "OrganizationUnitMoveConfirmMessage": "你確定要在「 {1}」下移動「 {0}」嗎？",
    "NoOrganizationUnits": "沒有組織機構!",
    "OrganizationUnitDuplicateDisplayNameWarning": "組織的顯示名稱已存在. 請嘗試其它顯示名稱.",
    "SecurityLogs": "安全日誌",
    "SecurityLogs:StartTime": "開始時間",
    "SecurityLogs:EndTime": "結束時間",
    "SecurityLogs:Application": "應用程式",
    "SecurityLogs:Identity": "標識",
    "SecurityLogs:Action": "操作",
    "SecurityLogs:UserName": "使用者名稱",
    "SecurityLogs:Client": "Client",
    "SecurityLogs:Time": "建立時間",
    "SecurityLogs:CorrelationId": "CorrelationId",
    "SecurityLogs:IpAddress": "IP地址",
    "SecurityLogs:Browser": "瀏覽器資訊",
    "InvalidLinkToken": "無效的關聯Token"
  }
}
